pictor_lib/__init__.py
pictor_lib/pictor_box.py
pictor_lib/pictor_drawable.py
pictor_lib/pictor_point.py
pictor_lib/pictor_rectangle.py
pictor_lib/pictor_size.py
pictor_lib/pictor_type.py
pictor_lib-0.8.4.dist-info/METADATA
pictor_lib-0.8.4.dist-info/WHEEL
pictor_lib-0.8.4.dist-info/licenses/LICENSE
pictor_lib-0.8.4.dist-info/RECORD
